dagwapi/__init__.py
dagwapi/atvr_iface.py
dagwapi/denon_iface.py
dagwapi/hubspace_iface.py
dagwapi/models/atvr.py
dagwapi/models/hs_device.py
dagwapi/models/receiver.py
dagwapi/utils/helper.py
da_gateway_api-0.2.16.dist-info/METADATA
da_gateway_api-0.2.16.dist-info/WHEEL
da_gateway_api-0.2.16.dist-info/RECORD
