Metadata-Version: 2.3
Name: da-gateway-api
Version: 0.2.16
Summary: 
Author: Al DAmico
Author-email: JavaWiz1@hotmail.com
Requires-Python: >=3.10,<4.0
Classifier: Programming Language :: Python :: 3
Classifier: Programming Language :: Python :: 3.10
Classifier: Programming Language :: Python :: 3.11
Classifier: Programming Language :: Python :: 3.12
Classifier: Programming Language :: Python :: 3.13
Requires-Dist: dt-foundation
Requires-Dist: dt-net
Requires-Dist: requests
